src/control_unit.v
/*
 * Control Unit Module
 * FSM-based control for instruction decode and signal generation
 * 
 * ADLD & CO Project - 8-bit RISC CPU
 */

module control_unit (
    input  wire        clk,              // Clock signal
    input  wire        reset,            // Reset signal
    input  wire [7:0]  instruction,      // Current instruction (from IR)
    input  wire        zero_flag,        // Zero flag from ALU
    
    // Control outputs
    output reg         pc_enable,        // Enable PC update
    output reg         pc_load,          // Load PC (for jumps)
    output reg         reg_write,        // Register write enable
    output reg         mem_write,        // Memory write enable
    output reg         mem_to_reg,       // Memory to register MUX
    output reg         use_imm,          // Use immediate for writeback
    output reg         ir_load,          // Instruction register load
    output reg         imm_load,         // Loading immediate value
    output reg         alu_latch,        // Latch ALU result
    output reg  [3:0]  alu_op,           // ALU operation
    output reg         halt              // CPU halt signal
);

    // Instruction opcodes
    localparam OP_NOP = 4'b0000;
    localparam OP_ADD = 4'b0001;
    localparam OP_SUB = 4'b0010;
    localparam OP_AND = 4'b0011;
    localparam OP_OR  = 4'b0100;
    localparam OP_XOR = 4'b0101;
    localparam OP_NOT = 4'b0110;
    localparam OP_SHL = 4'b0111;
    localparam OP_SHR = 4'b1000;
    localparam OP_LDI = 4'b1001;
    localparam OP_LD  = 4'b1010;
    localparam OP_ST  = 4'b1011;
    localparam OP_JMP = 4'b1100;
    localparam OP_JZ  = 4'b1101;
    localparam OP_HLT = 4'b1110;
    localparam OP_MOV = 4'b1111;

    // FSM States
    localparam STATE_FETCH     = 3'b000;
    localparam STATE_DECODE    = 3'b001;
    localparam STATE_EXECUTE   = 3'b010;
    localparam STATE_MEMORY    = 3'b011;
    localparam STATE_WRITEBACK = 3'b100;
    localparam STATE_HALT      = 3'b101;
    localparam STATE_FETCH_IMM = 3'b110;

    reg [2:0] state, next_state;
    
    // Latch opcode during decode
    reg [3:0] opcode_reg;
    wire [3:0] opcode = instruction[7:4];

    // State register
    always @(posedge clk or posedge reset) begin
        if (reset) begin
            state <= STATE_FETCH;
            opcode_reg <= 4'b0;
        end else begin
            state <= next_state;
            if (state == STATE_DECODE)
                opcode_reg <= opcode;
        end
    end

    // Next state logic
    always @(*) begin
        next_state = state;
        case (state)
            STATE_FETCH: begin
                next_state = STATE_DECODE;
            end
            
            STATE_DECODE: begin
                case (opcode)
                    OP_HLT:  next_state = STATE_HALT;
                    OP_LDI:  next_state = STATE_FETCH_IMM;
                    OP_JMP:  next_state = STATE_FETCH_IMM;
                    OP_JZ:   next_state = STATE_FETCH_IMM;
                    default: next_state = STATE_EXECUTE;
                endcase
            end
            
            STATE_FETCH_IMM: begin
                next_state = STATE_EXECUTE;
            end
            
            STATE_EXECUTE: begin
                if (opcode_reg == OP_LD || opcode_reg == OP_ST)
                    next_state = STATE_MEMORY;
                else
                    next_state = STATE_WRITEBACK;
            end
            
            STATE_MEMORY: begin
                next_state = STATE_WRITEBACK;
            end
            
            STATE_WRITEBACK: begin
                next_state = STATE_FETCH;
            end
            
            STATE_HALT: begin
                next_state = STATE_HALT;
            end
            
            default: next_state = STATE_FETCH;
        endcase
    end

    // Control signal generation
    always @(*) begin
        // Default values
        pc_enable  = 1'b0;
        pc_load    = 1'b0;
        reg_write  = 1'b0;
        mem_write  = 1'b0;
        mem_to_reg = 1'b0;
        use_imm    = 1'b0;
        ir_load    = 1'b0;
        imm_load   = 1'b0;
        alu_latch  = 1'b0;
        alu_op     = 4'b0000;
        halt       = 1'b0;

        case (state)
            STATE_FETCH: begin
                ir_load = 1'b1;    // Load instruction register
                pc_enable = 1'b1;  // Increment PC
            end
            
            STATE_DECODE: begin
                // Setup ALU opcode for next cycle
                alu_op = opcode;
            end
            
            STATE_FETCH_IMM: begin
                pc_enable = 1'b1;  // Move to next byte
                imm_load  = 1'b1;  // Load immediate value
            end
            
            STATE_EXECUTE: begin
                alu_op = opcode_reg;
                alu_latch = 1'b1;  // Latch ALU result
                case (opcode_reg)
                    OP_JMP: begin
                        pc_load = 1'b1;
                        pc_enable = 1'b1;
                    end
                    OP_JZ: begin
                        if (zero_flag) begin
                            pc_load = 1'b1;
                            pc_enable = 1'b1;
                        end
                    end
                    default: begin
                        // ALU operations - result latched
                    end
                endcase
            end
            
            STATE_MEMORY: begin
                if (opcode_reg == OP_ST) begin
                    mem_write = 1'b1;
                end
            end
            
            STATE_WRITEBACK: begin
                case (opcode_reg)
                    OP_NOP, OP_ST, OP_JMP, OP_JZ: begin
                        // No register write
                    end
                    OP_LD: begin
                        reg_write  = 1'b1;
                        mem_to_reg = 1'b1;
                    end
                    OP_LDI: begin
                        reg_write = 1'b1;
                        use_imm   = 1'b1;
                    end
                    default: begin
                        reg_write = 1'b1;  // Write latched ALU result
                    end
                endcase
            end
            
            STATE_HALT: begin
                halt = 1'b1;
            end
        endcase
    end

endmodule

src/data_memory.v
/*
 * Data Memory Module (RAM)
 * 256 x 8-bit read-write memory for data
 * 
 * ADLD & CO Project - 8-bit RISC CPU
 */

module data_memory (
    input  wire        clk,          // Clock signal
    input  wire        write_enable, // Write enable
    input  wire [7:0]  address,      // Memory address
    input  wire [7:0]  write_data,   // Data to write
    output wire [7:0]  read_data     // Data read from address
);

    // 256 bytes of data memory
    reg [7:0] memory [0:255];
    
    // Asynchronous read
    assign read_data = memory[address];
    
    // Synchronous write
    always @(posedge clk) begin
        if (write_enable) begin
            memory[address] <= write_data;
        end
    end
    
    // Initialize memory to zeros
    integer i;
    initial begin
        for (i = 0; i < 256; i = i + 1) begin
            memory[i] = 8'b0;
        end
    end

endmodule

src/alu.v
/*
 * ALU (Arithmetic Logic Unit) Module
 * 8-bit ALU with 8 operations
 * 
 * ADLD & CO Project - 8-bit RISC CPU
 */

module alu (
    input  wire [7:0] operand_a,    // First operand (from register Rd)
    input  wire [7:0] operand_b,    // Second operand (from register Rs)
    input  wire [3:0] alu_op,       // ALU operation select
    output reg  [7:0] result,       // Result of operation
    output wire       zero_flag     // Zero flag (1 if result is 0)
);

    // ALU Operation Codes
    localparam ALU_ADD = 4'b0001;   // Addition
    localparam ALU_SUB = 4'b0010;   // Subtraction
    localparam ALU_AND = 4'b0011;   // Bitwise AND
    localparam ALU_OR  = 4'b0100;   // Bitwise OR
    localparam ALU_XOR = 4'b0101;   // Bitwise XOR
    localparam ALU_NOT = 4'b0110;   // Bitwise NOT
    localparam ALU_SHL = 4'b0111;   // Shift Left
    localparam ALU_SHR = 4'b1000;   // Shift Right
    localparam ALU_MOV = 4'b1111;   // Move (pass through B)

    // Zero flag is set when result equals zero
    assign zero_flag = (result == 8'b0);

    // ALU operation logic (combinational)
    always @(*) begin
        case (alu_op)
            ALU_ADD: result = operand_a + operand_b;
            ALU_SUB: result = operand_a - operand_b;
            ALU_AND: result = operand_a & operand_b;
            ALU_OR:  result = operand_a | operand_b;
            ALU_XOR: result = operand_a ^ operand_b;
            ALU_NOT: result = ~operand_a;
            ALU_SHL: result = operand_a << 1;
            ALU_SHR: result = operand_a >> 1;
            ALU_MOV: result = operand_b;
            default: result = 8'b0;
        endcase
    end

endmodule

src/register_file.v
/*
 * Register File Module
 * 4 x 8-bit general purpose registers (R0-R3)
 * 
 * ADLD & CO Project - 8-bit RISC CPU
 */

module register_file (
    input  wire        clk,          // Clock signal
    input  wire        reset,        // Reset signal
    input  wire        write_enable, // Write enable
    input  wire [1:0]  read_addr1,   // Read address 1 (Rd)
    input  wire [1:0]  read_addr2,   // Read address 2 (Rs)
    input  wire [1:0]  write_addr,   // Write address
    input  wire [7:0]  write_data,   // Data to write
    output wire [7:0]  read_data1,   // Data from Rd
    output wire [7:0]  read_data2    // Data from Rs
);

    // 4 registers, 8 bits each
    reg [7:0] registers [0:3];
    
    // Asynchronous read (combinational)
    assign read_data1 = registers[read_addr1];
    assign read_data2 = registers[read_addr2];
    
    // Synchronous write
    integer i;
    always @(posedge clk or posedge reset) begin
        if (reset) begin
            // Clear all registers on reset
            for (i = 0; i < 4; i = i + 1) begin
                registers[i] <= 8'b0;
            end
        end else if (write_enable) begin
            registers[write_addr] <= write_data;
        end
    end

endmodule

src/instruction_mem.v
/*
 * Instruction Memory Module (ROM)
 * 256 x 8-bit read-only memory for instructions
 * 
 * ADLD & CO Project - 8-bit RISC CPU
 */

module instruction_memory (
    input  wire [7:0] address,       // Address to read
    output wire [7:0] instruction    // Instruction at address
);

    // 256 bytes of instruction memory
    reg [7:0] memory [0:255];
    
    // Asynchronous read
    assign instruction = memory[address];
    
    // Initialize with sample program
    // This program demonstrates all CPU operations
    initial begin
        // Program: Calculate (5 + 3) - 2, store result, then halt
        
        // LDI R0, 5    (Load 5 into R0)
        memory[0]  = 8'b1001_00_00;  // LDI opcode, Rd=R0
        memory[1]  = 8'd5;           // Immediate value = 5
        
        // LDI R1, 3    (Load 3 into R1)
        memory[2]  = 8'b1001_01_00;  // LDI opcode, Rd=R1
        memory[3]  = 8'd3;           // Immediate value = 3
        
        // ADD R0, R1   (R0 = R0 + R1 = 5 + 3 = 8)
        memory[4]  = 8'b0001_00_01;  // ADD opcode, Rd=R0, Rs=R1
        
        // LDI R2, 2    (Load 2 into R2)
        memory[5]  = 8'b1001_10_00;  // LDI opcode, Rd=R2
        memory[6]  = 8'd2;           // Immediate value = 2
        
        // SUB R0, R2   (R0 = R0 - R2 = 8 - 2 = 6)
        memory[7]  = 8'b0010_00_10;  // SUB opcode, Rd=R0, Rs=R2
        
        // LDI R3, 0    (Load memory address 0 into R3)
        memory[8]  = 8'b1001_11_00;  // LDI opcode, Rd=R3
        memory[9]  = 8'd0;           // Address = 0
        
        // ST R0, R3    (Store R0 to memory[R3] = memory[0])
        memory[10] = 8'b1011_00_11;  // ST opcode, Rd=R0, Rs=R3
        
        // HLT          (Halt the CPU)
        memory[11] = 8'b1110_00_00;  // HLT opcode
        
        // Fill remaining memory with NOP
        // (Handled by default initialization to 0)
    end

endmodule

src/program_counter.v
/*
 * Program Counter Module
 * 8-bit PC with increment and load functionality
 * 
 * ADLD & CO Project - 8-bit RISC CPU
 */

module program_counter (
    input  wire        clk,          // Clock signal
    input  wire        reset,        // Reset signal
    input  wire        pc_enable,    // Enable PC update
    input  wire        pc_load,      // Load new address (for jumps)
    input  wire [7:0]  pc_in,        // Address to load
    output reg  [7:0]  pc_out        // Current PC value
);

    always @(posedge clk or posedge reset) begin
        if (reset) begin
            pc_out <= 8'b0;          // Reset to address 0
        end else if (pc_enable) begin
            if (pc_load) begin
                pc_out <= pc_in;     // Jump to new address
            end else begin
                pc_out <= pc_out + 1; // Increment PC
            end
        end
    end

endmodule

src/cpu_top.v
/*
 * CPU Top Module
 * Integrates all components into a complete 8-bit RISC CPU
 * 
 * ADLD & CO Project - 8-bit RISC CPU
 */

module cpu_top (
    input  wire        clk,          // Clock signal
    input  wire        reset,        // Reset signal
    output wire        halt,         // CPU halted indicator
    output wire [7:0]  pc_out,       // Program counter (for debug)
    output wire [7:0]  alu_result    // ALU result (for debug)
);

    // Internal wires
    wire [7:0] instruction_from_mem;
    wire [7:0] reg_data1, reg_data2;
    wire [7:0] alu_out;
    wire [7:0] mem_read_data;
    reg  [7:0] write_back_data;
    wire       zero_flag;
    
    // Control signals
    wire       pc_enable, pc_load;
    wire       reg_write;
    wire       mem_write;
    wire       mem_to_reg;
    wire       imm_load;
    wire       ir_load;
    wire       alu_latch;      // Latch ALU result
    wire [3:0] alu_op;
    wire       use_imm;
    
    // Instruction Register - latches instruction during FETCH
    reg [7:0] instruction_reg;
    wire [7:0] instruction = instruction_reg;
    
    always @(posedge clk or posedge reset) begin
        if (reset)
            instruction_reg <= 8'b0;
        else if (ir_load)
            instruction_reg <= instruction_from_mem;
    end
    
    // Instruction decode from latched instruction
    wire [3:0] opcode = instruction[7:4];
    wire [1:0] rd     = instruction[3:2];
    wire [1:0] rs     = instruction[1:0];
    
    // Immediate value register - latches during FETCH_IMM
    reg [7:0] imm_reg;
    always @(posedge clk or posedge reset) begin
        if (reset)
            imm_reg <= 8'b0;
        else if (imm_load)
            imm_reg <= instruction_from_mem;
    end
    
    // ALU result register - latches during EXECUTE
    reg [7:0] alu_result_reg;
    always @(posedge clk or posedge reset) begin
        if (reset)
            alu_result_reg <= 8'b0;
        else if (alu_latch)
            alu_result_reg <= alu_out;
    end
    
    // ALU operand B selection
    wire [7:0] alu_operand_b = reg_data2;
    
    // Write-back data selection - controlled by control unit signals
    always @(*) begin
        if (mem_to_reg)
            write_back_data = mem_read_data;
        else if (use_imm)
            write_back_data = imm_reg;
        else
            write_back_data = alu_result_reg;  // Use latched result
    end
    
    // Debug outputs
    assign alu_result = alu_out;

    // =====================================================
    // Module Instantiations
    // =====================================================
    
    // Program Counter
    program_counter pc_inst (
        .clk        (clk),
        .reset      (reset),
        .pc_enable  (pc_enable),
        .pc_load    (pc_load),
        .pc_in      (imm_reg),
        .pc_out     (pc_out)
    );
    
    // Instruction Memory (ROM)
    instruction_memory imem_inst (
        .address    (pc_out),
        .instruction(instruction_from_mem)
    );
    
    // Register File
    register_file regfile_inst (
        .clk         (clk),
        .reset       (reset),
        .write_enable(reg_write),
        .read_addr1  (rd),
        .read_addr2  (rs),
        .write_addr  (rd),
        .write_data  (write_back_data),
        .read_data1  (reg_data1),
        .read_data2  (reg_data2)
    );
    
    // ALU
    alu alu_inst (
        .operand_a  (reg_data1),
        .operand_b  (alu_operand_b),
        .alu_op     (alu_op),
        .result     (alu_out),
        .zero_flag  (zero_flag)
    );
    
    // Data Memory (RAM)
    data_memory dmem_inst (
        .clk         (clk),
        .write_enable(mem_write),
        .address     (reg_data2),
        .write_data  (reg_data1),
        .read_data   (mem_read_data)
    );
    
    // Control Unit
    control_unit ctrl_inst (
        .clk        (clk),
        .reset      (reset),
        .instruction(instruction),
        .zero_flag  (zero_flag),
        .pc_enable  (pc_enable),
        .pc_load    (pc_load),
        .reg_write  (reg_write),
        .mem_write  (mem_write),
        .mem_to_reg (mem_to_reg),
        .use_imm    (use_imm),
        .ir_load    (ir_load),
        .imm_load   (imm_load),
        .alu_latch  (alu_latch),
        .alu_op     (alu_op),
        .halt       (halt)
    );

endmodule

testbench/cpu_tb.v
/*
 * CPU Testbench
 * Simulates the 8-bit RISC CPU and displays execution trace
 * 
 * ADLD & CO Project - 8-bit RISC CPU
 */

`timescale 1ns/1ps

module cpu_tb;

    // Testbench signals
    reg        clk;
    reg        reset;
    wire       halt;
    wire [7:0] pc_out;
    wire [7:0] alu_result;
    
    // Instantiate CPU
    cpu_top cpu (
        .clk        (clk),
        .reset      (reset),
        .halt       (halt),
        .pc_out     (pc_out),
        .alu_result (alu_result)
    );
    
    // Clock generation (10ns period = 100MHz)
    initial begin
        clk = 0;
        forever #5 clk = ~clk;
    end
    
    // VCD dump for waveform viewing
    initial begin
        $dumpfile("cpu_waveform.vcd");
        $dumpvars(0, cpu_tb);
    end
    
    // Test sequence
    initial begin
        $display("========================================");
        $display("  8-bit RISC CPU Simulation");
        $display("  ADLD & CO Project");
        $display("========================================");
        $display("");
        
        // Apply reset
        reset = 1;
        #20;
        reset = 0;
        
        $display("Time\tPC\tInstruction\tR0\tR1\tR2\tR3\tALU Out\tState");
        $display("----\t--\t-----------\t--\t--\t--\t--\t-------\t-----");
        
        // Run simulation for enough cycles
        repeat (100) begin
            @(posedge clk);
            #1; // Small delay to let signals settle
            
            $display("%0t\t%d\t%b\t%d\t%d\t%d\t%d\t%d\t%d",
                $time,
                pc_out,
                cpu.imem_inst.memory[pc_out],
                cpu.regfile_inst.registers[0],
                cpu.regfile_inst.registers[1],
                cpu.regfile_inst.registers[2],
                cpu.regfile_inst.registers[3],
                alu_result,
                cpu.ctrl_inst.state
            );
            
            // Stop when CPU halts
            if (halt) begin
                $display("");
                $display("========================================");
                $display("  CPU HALTED");
                $display("========================================");
                $display("");
                $display("Final Register Values:");
                $display("  R0 = %d (expected: 6)", cpu.regfile_inst.registers[0]);
                $display("  R1 = %d (expected: 3)", cpu.regfile_inst.registers[1]);
                $display("  R2 = %d (expected: 2)", cpu.regfile_inst.registers[2]);
                $display("  R3 = %d (expected: 0)", cpu.regfile_inst.registers[3]);
                $display("");
                $display("Data Memory[0] = %d (expected: 6)", cpu.dmem_inst.memory[0]);
                $display("");
                
                // Verify results
                if (cpu.regfile_inst.registers[0] == 6 &&
                    cpu.dmem_inst.memory[0] == 6) begin
                    $display("*** TEST PASSED ***");
                end else begin
                    $display("*** TEST FAILED ***");
                end
                
                $finish;
            end
        end
        
        $display("Simulation timeout - CPU did not halt");
        $finish;
    end

endmodule

cpu_waveform.vcd
$date
	Tue Jan 20 20:07:34 2026
$end
$version
	Icarus Verilog
$end
$timescale
	1ps
$end
$scope module cpu_tb $end
$var wire 8 ! pc_out [7:0] $end
$var wire 1 " halt $end
$var wire 8 # alu_result [7:0] $end
$var reg 1 $ clk $end
$var reg 1 % reset $end
$scope module cpu $end
$var wire 8 & alu_operand_b [7:0] $end
$var wire 8 ' alu_result [7:0] $end
$var wire 1 $ clk $end
$var wire 1 % reset $end
$var wire 1 ( zero_flag $end
$var wire 1 ) use_imm $end
$var wire 2 * rs [1:0] $end
$var wire 1 + reg_write $end
$var wire 8 , reg_data2 [7:0] $end
$var wire 8 - reg_data1 [7:0] $end
$var wire 2 . rd [1:0] $end
$var wire 8 / pc_out [7:0] $end
$var wire 1 0 pc_load $end
$var wire 1 1 pc_enable $end
$var wire 4 2 opcode [3:0] $end
$var wire 1 3 mem_write $end
$var wire 1 4 mem_to_reg $end
$var wire 8 5 mem_read_data [7:0] $end
$var wire 1 6 ir_load $end
$var wire 8 7 instruction_from_mem [7:0] $end
$var wire 8 8 instruction [7:0] $end
$var wire 1 9 imm_load $end
$var wire 1 " halt $end
$var wire 8 : alu_out [7:0] $end
$var wire 4 ; alu_op [3:0] $end
$var wire 1 < alu_latch $end
$var reg 8 = alu_result_reg [7:0] $end
$var reg 8 > imm_reg [7:0] $end
$var reg 8 ? instruction_reg [7:0] $end
$var reg 8 @ write_back_data [7:0] $end
$scope module alu_inst $end
$var wire 8 A operand_b [7:0] $end
$var wire 1 ( zero_flag $end
$var wire 8 B operand_a [7:0] $end
$var wire 4 C alu_op [3:0] $end
$var parameter 4 D ALU_ADD $end
$var parameter 4 E ALU_AND $end
$var parameter 4 F ALU_MOV $end
$var parameter 4 G ALU_NOT $end
$var parameter 4 H ALU_OR $end
$var parameter 4 I ALU_SHL $end
$var parameter 4 J ALU_SHR $end
$var parameter 4 K ALU_SUB $end
$var parameter 4 L ALU_XOR $end
$var reg 8 M result [7:0] $end
$upscope $end
$scope module ctrl_inst $end
$var wire 1 $ clk $end
$var wire 8 N instruction [7:0] $end
$var wire 1 % reset $end
$var wire 1 ( zero_flag $end
$var wire 4 O opcode [3:0] $end
$var parameter 4 P OP_ADD $end
$var parameter 4 Q OP_AND $end
$var parameter 4 R OP_HLT $end
$var parameter 4 S OP_JMP $end
$var parameter 4 T OP_JZ $end
$var parameter 4 U OP_LD $end
$var parameter 4 V OP_LDI $end
$var parameter 4 W OP_MOV $end
$var parameter 4 X OP_NOP $end
$var parameter 4 Y OP_NOT $end
$var parameter 4 Z OP_OR $end
$var parameter 4 [ OP_SHL $end
$var parameter 4 \ OP_SHR $end
$var parameter 4 ] OP_ST $end
$var parameter 4 ^ OP_SUB $end
$var parameter 4 _ OP_XOR $end
$var parameter 3 ` STATE_DECODE $end
$var parameter 3 a STATE_EXECUTE $end
$var parameter 3 b STATE_FETCH $end
$var parameter 3 c STATE_FETCH_IMM $end
$var parameter 3 d STATE_HALT $end
$var parameter 3 e STATE_MEMORY $end
$var parameter 3 f STATE_WRITEBACK $end
$var reg 1 < alu_latch $end
$var reg 4 g alu_op [3:0] $end
$var reg 1 " halt $end
$var reg 1 9 imm_load $end
$var reg 1 6 ir_load $end
$var reg 1 4 mem_to_reg $end
$var reg 1 3 mem_write $end
$var reg 3 h next_state [2:0] $end
$var reg 4 i opcode_reg [3:0] $end
$var reg 1 1 pc_enable $end
$var reg 1 0 pc_load $end
$var reg 1 + reg_write $end
$var reg 3 j state [2:0] $end
$var reg 1 ) use_imm $end
$upscope $end
$scope module dmem_inst $end
$var wire 1 $ clk $end
$var wire 8 k read_data [7:0] $end
$var wire 1 3 write_enable $end
$var wire 8 l write_data [7:0] $end
$var wire 8 m address [7:0] $end
$var integer 32 n i [31:0] $end
$upscope $end
$scope module imem_inst $end
$var wire 8 o instruction [7:0] $end
$var wire 8 p address [7:0] $end
$upscope $end
$scope module pc_inst $end
$var wire 1 $ clk $end
$var wire 1 1 pc_enable $end
$var wire 8 q pc_in [7:0] $end
$var wire 1 0 pc_load $end
$var wire 1 % reset $end
$var reg 8 r pc_out [7:0] $end
$upscope $end
$scope module regfile_inst $end
$var wire 1 $ clk $end
$var wire 2 s read_addr1 [1:0] $end
$var wire 2 t read_addr2 [1:0] $end
$var wire 8 u read_data1 [7:0] $end
$var wire 8 v read_data2 [7:0] $end
$var wire 1 % reset $end
$var wire 2 w write_addr [1:0] $end
$var wire 8 x write_data [7:0] $end
$var wire 1 + write_enable $end
$var integer 32 y i [31:0] $end
$upscope $end
$upscope $end
$upscope $end
$enddefinitions $end
$comment Show the parameter values. $end
$dumpall
b100 f
b11 e
b101 d
b110 c
b0 b
b10 a
b1 `
b101 _
b10 ^
b1011 ]
b1000 \
b111 [
b100 Z
b110 Y
b0 X
b1111 W
b1001 V
b1010 U
b1101 T
b1100 S
b1110 R
b11 Q
b1 P
b101 L
b10 K
b1000 J
b111 I
b100 H
b110 G
b1111 F
b11 E
b1 D
$end
#0
$dumpvars
b100 y
b0 x
b0 w
b0 v
b0 u
b0 t
b0 s
b0 r
b0 q
b0 p
b10010000 o
b100000000 n
b0 m
b0 l
b0 k
b0 j
b0 i
b1 h
b0 g
b0 O
b0 N
b0 M
b0 C
b0 B
b0 A
b0 @
b0 ?
b0 >
b0 =
0<
b0 ;
b0 :
09
b0 8
b10010000 7
16
b0 5
04
03
b0 2
11
00
b0 /
b0 .
b0 -
b0 ,
0+
b0 *
0)
1(
b0 '
b0 &
1%
0$
b0 #
0"
b0 !
$end
#5000
b100 y
1$
#10000
0$
#15000
b100 y
1$
#20000
0$
0%
#25000
b1001 ;
b1001 C
b1001 g
b1001 2
b1001 O
06
01
b110 h
b10010000 8
b10010000 ?
b10010000 N
b1 j
b101 7
b101 o
b1 !
b1 /
b1 p
b1 r
1$
#30000
0$
#35000
19
11
b0 ;
b0 C
b0 g
b10 h
b1001 i
b110 j
1$
#40000
0$
#45000
1<
b1001 ;
b1001 C
b1001 g
09
01
b100 h
b101 >
b101 q
b10 j
b10010100 7
b10010100 o
b10 !
b10 /
b10 p
b10 r
1$
#50000
0$
#55000
b101 @
b101 x
1)
1+
b0 ;
b0 C
b0 g
0<
b0 h
b100 j
1$
#60000
0$
#65000
b0 @
b0 x
11
16
0)
0+
b1 h
b0 j
b101 -
b101 B
b101 l
b101 u
b101 &
b101 A
b101 ,
b101 m
b101 v
1$
#70000
0$
#75000
b1001 ;
b1001 C
b1001 g
06
01
b110 h
b0 -
b0 B
b0 l
b0 u
b1 .
b1 s
b1 w
b11 7
b11 o
b11 !
b11 /
b11 p
b11 r
b1 j
b10010100 8
b10010100 ?
b10010100 N
1$
#80000
0$
#85000
19
11
b0 ;
b0 C
b0 g
b10 h
b110 j
1$
#90000
0$
#95000
1<
b1001 ;
b1001 C
b1001 g
09
01
b100 h
b10001 7
b10001 o
b100 !
b100 /
b100 p
b100 r
b10 j
b11 >
b11 q
1$
#100000
0$
#105000
b11 @
b11 x
1)
1+
b0 ;
b0 C
b0 g
0<
b0 h
b100 j
1$
#110000
0$
#115000
b0 @
b0 x
11
16
0)
0+
b1 h
b11 -
b11 B
b11 l
b11 u
b0 j
1$
#120000
0$
#125000
0(
b1000 #
b1000 '
b1000 :
b1000 M
b1 2
b101 -
b101 B
b101 l
b101 u
b0 .
b0 s
b0 w
b11 &
b11 A
b11 ,
b11 m
b11 v
b1 *
b1 t
b1 O
b1 ;
b1 C
b1 g
06
01
b10 h
b10001 8
b10001 ?
b10001 N
b1 j
b10011000 7
b10011000 o
b101 !
b101 /
b101 p
b101 r
1$
#130000
0$
#135000
1<
b1 ;
b1 C
b1 g
b100 h
b1 i
b10 j
1$
#140000
0$
#145000
1(
b0 #
b0 '
b0 :
b0 M
b1000 @
b1000 x
1+
b0 ;
b0 C
b0 g
0<
b0 h
b1000 =
b100 j
1$
#150000
0$
#155000
11
16
0+
b1 h
b1000 -
b1000 B
b1000 l
b1000 u
b0 j
1$
#160000
0$
#165000
1(
b0 #
b0 '
b0 :
b0 M
b1001 2
b0 -
b0 B
b0 l
b0 u
b10 .
b10 s
b10 w
b1000 &
b1000 A
b1000 ,
b1000 m
b1000 v
b0 *
b0 t
b1001 O
b1001 ;
b1001 C
b1001 g
06
01
b110 h
b10011000 8
b10011000 ?
b10011000 N
b1 j
b10 7
b10 o
b110 !
b110 /
b110 p
b110 r
1$
#170000
0$
#175000
19
11
b0 ;
b0 C
b0 g
b10 h
b1001 i
b110 j
1$
#180000
0$
#185000
1<
b1001 ;
b1001 C
b1001 g
09
01
b100 h
b10 >
b10 q
b10 j
b100010 7
b100010 o
b111 !
b111 /
b111 p
b111 r
1$
#190000
0$
#195000
1)
1+
b0 ;
b0 C
b0 g
0<
b0 h
b10 @
b10 x
b100 j
b0 =
1$
#200000
0$
#205000
b0 @
b0 x
11
16
0)
0+
b1 h
b0 j
b10 -
b10 B
b10 l
b10 u
1$
#210000
0$
#215000
0(
b110 #
b110 '
b110 :
b110 M
b10 ;
b10 C
b10 g
06
01
b10 h
b10 2
b1000 -
b1000 B
b1000 l
b1000 u
b0 .
b0 s
b0 w
b10 &
b10 A
b10 ,
b10 m
b10 v
b10 *
b10 t
b10 O
b10011100 7
b10011100 o
b1000 !
b1000 /
b1000 p
b1000 r
b1 j
b100010 8
b100010 ?
b100010 N
1$
#220000
0$
#225000
1<
b10 ;
b10 C
b10 g
b100 h
b10 i
b10 j
1$
#230000
0$
#235000
1(
b0 #
b0 '
b0 :
b0 M
1+
b0 ;
b0 C
b0 g
0<
b0 h
b110 @
b110 x
b100 j
b110 =
1$
#240000
0$
#245000
11
16
0+
b1 h
b0 j
b110 -
b110 B
b110 l
b110 u
1$
#250000
0$
#255000
b1001 ;
b1001 C
b1001 g
06
01
b110 h
b1001 2
b0 -
b0 B
b0 l
b0 u
b11 .
b11 s
b11 w
b110 &
b110 A
b110 ,
b110 m
b110 v
b0 *
b0 t
b1001 O
b0 7
b0 o
b1001 !
b1001 /
b1001 p
b1001 r
b1 j
b10011100 8
b10011100 ?
b10011100 N
1$
#260000
0$
#265000
19
11
b0 ;
b0 C
b0 g
b10 h
b1001 i
b110 j
1$
#270000
0$
#275000
1<
b1001 ;
b1001 C
b1001 g
09
01
b100 h
b10110011 7
b10110011 o
b1010 !
b1010 /
b1010 p
b1010 r
b10 j
b0 >
b0 q
1$
#280000
0$
#285000
b0 @
b0 x
1)
1+
b0 ;
b0 C
b0 g
0<
b0 h
b0 =
b100 j
1$
#290000
0$
#295000
11
16
0)
0+
b1 h
b0 j
1$
#300000
0$
#305000
b1011 2
b110 -
b110 B
b110 l
b110 u
b0 .
b0 s
b0 w
b0 &
b0 A
b0 ,
b0 m
b0 v
b11 *
b11 t
b1011 O
b1011 ;
b1011 C
b1011 g
06
01
b10 h
b10110011 8
b10110011 ?
b10110011 N
b1 j
b11100000 7
b11100000 o
b1011 !
b1011 /
b1011 p
b1011 r
1$
#310000
0$
#315000
1<
b1011 ;
b1011 C
b1011 g
b11 h
b1011 i
b10 j
1$
#320000
0$
#325000
13
b0 ;
b0 C
b0 g
0<
b100 h
b11 j
1$
#330000
0$
#335000
03
b0 h
b100 j
b110 5
b110 k
1$
#340000
0$
#345000
11
16
b1 h
b0 j
1$
#350000
0$
#355000
b1110 ;
b1110 C
b1110 g
06
01
b101 h
b1110 2
b0 5
b0 k
b110 &
b110 A
b110 ,
b110 m
b110 v
b0 *
b0 t
b1110 O
bx 7
bx o
b1100 !
b1100 /
b1100 p
b1100 r
b1 j
b11100000 8
b11100000 ?
b11100000 N
1$
#360000
0$
#365000
1"
b0 ;
b0 C
b0 g
b1110 i
b101 j
1$
