src/control_unit.v
/*
 * Control Unit Module
 * FSM-based control for instruction decode and signal generation
 * 
 * ADLD & CO Project - 16-bit RISC CPU
 * 
 * 16-bit Instruction Format:
 * [15:12] - Opcode (4 bits)
 * [11:10] - Rd (destination register, 2 bits)
 * [9:8]   - Rs (source register, 2 bits)
 * [7:0]   - Immediate value (8 bits)
 */

module control_unit (
    input  wire         clk,              // Clock signal
    input  wire         reset,            // Reset signal
    input  wire [15:0]  instruction,      // Current instruction (from IR)
    input  wire         zero_flag,        // Zero flag from ALU
    
    // Control outputs
    output reg          pc_enable,        // Enable PC update
    output reg          pc_load,          // Load PC (for jumps)
    output reg          reg_write,        // Register write enable
    output reg          mem_write,        // Memory write enable
    output reg          mem_to_reg,       // Memory to register MUX
    output reg          use_imm,          // Use immediate for writeback
    output reg          ir_load,          // Instruction register load
    output reg          alu_latch,        // Latch ALU result
    output reg  [3:0]   alu_op,           // ALU operation
    output reg          halt              // CPU halt signal
);

    // Instruction opcodes
    localparam OP_NOP = 4'b0000;
    localparam OP_ADD = 4'b0001;
    localparam OP_SUB = 4'b0010;
    localparam OP_AND = 4'b0011;
    localparam OP_OR  = 4'b0100;
    localparam OP_XOR = 4'b0101;
    localparam OP_NOT = 4'b0110;
    localparam OP_SHL = 4'b0111;
    localparam OP_SHR = 4'b1000;
    localparam OP_LDI = 4'b1001;
    localparam OP_LD  = 4'b1010;
    localparam OP_ST  = 4'b1011;
    localparam OP_JMP = 4'b1100;
    localparam OP_JZ  = 4'b1101;
    localparam OP_HLT = 4'b1110;
    localparam OP_MOV = 4'b1111;

    // FSM States (simplified - no FETCH_IMM needed with 16-bit instructions)
    localparam STATE_FETCH     = 3'b000;
    localparam STATE_DECODE    = 3'b001;
    localparam STATE_EXECUTE   = 3'b010;
    localparam STATE_MEMORY    = 3'b011;
    localparam STATE_WRITEBACK = 3'b100;
    localparam STATE_HALT      = 3'b101;

    reg [2:0] state, next_state;
    
    // Latch opcode during decode
    reg [3:0] opcode_reg;
    wire [3:0] opcode = instruction[15:12];

    // State register
    always @(posedge clk or posedge reset) begin
        if (reset) begin
            state <= STATE_FETCH;
            opcode_reg <= 4'b0;
        end else begin
            state <= next_state;
            if (state == STATE_DECODE)
                opcode_reg <= opcode;
        end
    end

    // Next state logic
    always @(*) begin
        next_state = state;
        case (state)
            STATE_FETCH: begin
                next_state = STATE_DECODE;
            end
            
            STATE_DECODE: begin
                case (opcode)
                    OP_HLT:  next_state = STATE_HALT;
                    default: next_state = STATE_EXECUTE;
                endcase
            end
            
            STATE_EXECUTE: begin
                if (opcode_reg == OP_LD || opcode_reg == OP_ST)
                    next_state = STATE_MEMORY;
                else
                    next_state = STATE_WRITEBACK;
            end
            
            STATE_MEMORY: begin
                next_state = STATE_WRITEBACK;
            end
            
            STATE_WRITEBACK: begin
                next_state = STATE_FETCH;
            end
            
            STATE_HALT: begin
                next_state = STATE_HALT;
            end
            
            default: next_state = STATE_FETCH;
        endcase
    end

    // Control signal generation
    always @(*) begin
        // Default values
        pc_enable  = 1'b0;
        pc_load    = 1'b0;
        reg_write  = 1'b0;
        mem_write  = 1'b0;
        mem_to_reg = 1'b0;
        use_imm    = 1'b0;
        ir_load    = 1'b0;
        alu_latch  = 1'b0;
        alu_op     = 4'b0000;
        halt       = 1'b0;

        case (state)
            STATE_FETCH: begin
                ir_load = 1'b1;    // Load instruction register
                pc_enable = 1'b1;  // Increment PC
            end
            
            STATE_DECODE: begin
                // Setup ALU opcode for next cycle
                alu_op = opcode;
            end
            
            STATE_EXECUTE: begin
                alu_op = opcode_reg;
                alu_latch = 1'b1;  // Latch ALU result
                case (opcode_reg)
                    OP_JMP: begin
                        pc_load = 1'b1;
                        pc_enable = 1'b1;
                    end
                    OP_JZ: begin
                        if (zero_flag) begin
                            pc_load = 1'b1;
                            pc_enable = 1'b1;
                        end
                    end
                    default: begin
                        // ALU operations - result latched
                    end
                endcase
            end
            
            STATE_MEMORY: begin
                if (opcode_reg == OP_ST) begin
                    mem_write = 1'b1;
                end
            end
            
            STATE_WRITEBACK: begin
                case (opcode_reg)
                    OP_NOP, OP_ST, OP_JMP, OP_JZ: begin
                        // No register write
                    end
                    OP_LD: begin
                        reg_write  = 1'b1;
                        mem_to_reg = 1'b1;
                    end
                    OP_LDI: begin
                        reg_write = 1'b1;
                        use_imm   = 1'b1;
                    end
                    default: begin
                        reg_write = 1'b1;  // Write latched ALU result
                    end
                endcase
            end
            
            STATE_HALT: begin
                halt = 1'b1;
            end
        endcase
    end

endmodule

src/data_memory.v
/*
 * Data Memory Module (RAM)
 * 256 x 16-bit read-write memory for data
 * 
 * ADLD & CO Project - 16-bit RISC CPU
 */

module data_memory (
    input  wire         clk,          // Clock signal
    input  wire         write_enable, // Write enable
    input  wire [15:0]  address,      // Memory address
    input  wire [15:0]  write_data,   // Data to write
    output wire [15:0]  read_data     // Data read from address
);

    // 256 words of 16-bit data memory
    reg [15:0] memory [0:255];
    
    // Asynchronous read (use lower 8 bits of address)
    assign read_data = memory[address[7:0]];
    
    // Synchronous write
    always @(posedge clk) begin
        if (write_enable) begin
            memory[address[7:0]] <= write_data;
        end
    end
    
    // Initialize memory to zeros
    integer i;
    initial begin
        for (i = 0; i < 256; i = i + 1) begin
            memory[i] = 16'b0;
        end
    end

endmodule

src/alu.v
/*
 * ALU (Arithmetic Logic Unit) Module
 * 16-bit ALU with 8 operations
 * 
 * ADLD & CO Project - 16-bit RISC CPU
 */

module alu (
    input  wire [15:0] operand_a,   // First operand (from register Rd)
    input  wire [15:0] operand_b,   // Second operand (from register Rs)
    input  wire [3:0]  alu_op,      // ALU operation select
    output reg  [15:0] result,      // Result of operation
    output wire        zero_flag    // Zero flag (1 if result is 0)
);

    // ALU Operation Codes
    localparam ALU_ADD = 4'b0001;   // Addition
    localparam ALU_SUB = 4'b0010;   // Subtraction
    localparam ALU_AND = 4'b0011;   // Bitwise AND
    localparam ALU_OR  = 4'b0100;   // Bitwise OR
    localparam ALU_XOR = 4'b0101;   // Bitwise XOR
    localparam ALU_NOT = 4'b0110;   // Bitwise NOT
    localparam ALU_SHL = 4'b0111;   // Shift Left
    localparam ALU_SHR = 4'b1000;   // Shift Right
    localparam ALU_MOV = 4'b1111;   // Move (pass through B)

    // Zero flag is set when result equals zero
    assign zero_flag = (result == 16'b0);

    // ALU operation logic (combinational)
    always @(*) begin
        case (alu_op)
            ALU_ADD: result = operand_a + operand_b;
            ALU_SUB: result = operand_a - operand_b;
            ALU_AND: result = operand_a & operand_b;
            ALU_OR:  result = operand_a | operand_b;
            ALU_XOR: result = operand_a ^ operand_b;
            ALU_NOT: result = ~operand_a;
            ALU_SHL: result = operand_a << 1;
            ALU_SHR: result = operand_a >> 1;
            ALU_MOV: result = operand_b;
            default: result = 16'b0;
        endcase
    end

endmodule

src/register_file.v
/*
 * Register File Module
 * 4 x 16-bit general purpose registers (R0-R3)
 * 
 * ADLD & CO Project - 16-bit RISC CPU
 */

module register_file (
    input  wire         clk,          // Clock signal
    input  wire         reset,        // Reset signal
    input  wire         write_enable, // Write enable
    input  wire [1:0]   read_addr1,   // Read address 1 (Rd)
    input  wire [1:0]   read_addr2,   // Read address 2 (Rs)
    input  wire [1:0]   write_addr,   // Write address
    input  wire [15:0]  write_data,   // Data to write
    output wire [15:0]  read_data1,   // Data from Rd
    output wire [15:0]  read_data2    // Data from Rs
);

    // 4 registers, 16 bits each
    reg [15:0] registers [0:3];
    
    // Asynchronous read (combinational)
    assign read_data1 = registers[read_addr1];
    assign read_data2 = registers[read_addr2];
    
    // Synchronous write
    integer i;
    always @(posedge clk or posedge reset) begin
        if (reset) begin
            // Clear all registers on reset
            for (i = 0; i < 4; i = i + 1) begin
                registers[i] <= 16'b0;
            end
        end else if (write_enable) begin
            registers[write_addr] <= write_data;
        end
    end

endmodule

src/instruction_mem.v
/*
 * Instruction Memory Module (ROM)
 * 256 x 16-bit read-only memory for instructions
 * 
 * ADLD & CO Project - 16-bit RISC CPU
 * 
 * 16-bit Instruction Format:
 * [15:12] - Opcode (4 bits)
 * [11:10] - Rd (destination register, 2 bits)
 * [9:8]   - Rs (source register, 2 bits)
 * [7:0]   - Immediate value (8 bits, for LDI/JMP/JZ)
 */

module instruction_memory (
    input  wire [15:0] address,      // Address to read
    output wire [15:0] instruction   // Instruction at address
);

    // 256 words of 16-bit instruction memory
    reg [15:0] memory [0:255];
    
    // Asynchronous read (use lower 8 bits of address)
    assign instruction = memory[address[7:0]];
    
    // Initialize with sample program
    // This program demonstrates all CPU operations
    // New 16-bit format: {opcode[4], Rd[2], Rs[2], imm[8]}
    initial begin
        // Program: Calculate (5 + 3) - 2, store result, then halt
        
        // LDI R0, 5    (Load 5 into R0)
        // Opcode=1001, Rd=00, Rs=00, Imm=00000101
        memory[0]  = 16'b1001_00_00_00000101;
        
        // LDI R1, 3    (Load 3 into R1)
        // Opcode=1001, Rd=01, Rs=00, Imm=00000011
        memory[1]  = 16'b1001_01_00_00000011;
        
        // ADD R0, R1   (R0 = R0 + R1 = 5 + 3 = 8)
        // Opcode=0001, Rd=00, Rs=01, Imm=00000000
        memory[2]  = 16'b0001_00_01_00000000;
        
        // LDI R2, 2    (Load 2 into R2)
        // Opcode=1001, Rd=10, Rs=00, Imm=00000010
        memory[3]  = 16'b1001_10_00_00000010;
        
        // SUB R0, R2   (R0 = R0 - R2 = 8 - 2 = 6)
        // Opcode=0010, Rd=00, Rs=10, Imm=00000000
        memory[4]  = 16'b0010_00_10_00000000;
        
        // LDI R3, 0    (Load memory address 0 into R3)
        // Opcode=1001, Rd=11, Rs=00, Imm=00000000
        memory[5]  = 16'b1001_11_00_00000000;
        
        // ST R0, R3    (Store R0 to memory[R3] = memory[0])
        // Opcode=1011, Rd=00, Rs=11, Imm=00000000
        memory[6]  = 16'b1011_00_11_00000000;
        
        // HLT          (Halt the CPU)
        // Opcode=1110, Rd=00, Rs=00, Imm=00000000
        memory[7]  = 16'b1110_00_00_00000000;
        
        // Fill remaining memory with NOP (default 0)
    end

endmodule

src/program_counter.v
/*
 * Program Counter Module
 * 16-bit PC with increment and load functionality
 * 
 * ADLD & CO Project - 16-bit RISC CPU
 */

module program_counter (
    input  wire         clk,          // Clock signal
    input  wire         reset,        // Reset signal
    input  wire         pc_enable,    // Enable PC update
    input  wire         pc_load,      // Load new address (for jumps)
    input  wire [15:0]  pc_in,        // Address to load
    output reg  [15:0]  pc_out        // Current PC value
);

    always @(posedge clk or posedge reset) begin
        if (reset) begin
            pc_out <= 16'b0;          // Reset to address 0
        end else if (pc_enable) begin
            if (pc_load) begin
                pc_out <= pc_in;      // Jump to new address
            end else begin
                pc_out <= pc_out + 1; // Increment PC
            end
        end
    end

endmodule

src/cpu_top.v
/*
 * CPU Top Module
 * Integrates all components into a complete 16-bit RISC CPU
 * 
 * ADLD & CO Project - 16-bit RISC CPU
 * 
 * 16-bit Instruction Format:
 * [15:12] - Opcode (4 bits)
 * [11:10] - Rd (destination register, 2 bits)
 * [9:8]   - Rs (source register, 2 bits)
 * [7:0]   - Immediate value (8 bits)
 */

module cpu_top (
    input  wire         clk,          // Clock signal
    input  wire         reset,        // Reset signal
    output wire         halt,         // CPU halted indicator
    output wire [15:0]  pc_out,       // Program counter (for debug)
    output wire [15:0]  alu_result    // ALU result (for debug)
);

    // Internal wires - all 16-bit data paths
    wire [15:0] instruction_from_mem;
    wire [15:0] reg_data1, reg_data2;
    wire [15:0] alu_out;
    wire [15:0] mem_read_data;
    reg  [15:0] write_back_data;
    wire        zero_flag;
    
    // Control signals
    wire       pc_enable, pc_load;
    wire       reg_write;
    wire       mem_write;
    wire       mem_to_reg;
    wire       ir_load;
    wire       alu_latch;
    wire [3:0] alu_op;
    wire       use_imm;
    
    // Instruction Register - latches instruction during FETCH
    reg [15:0] instruction_reg;
    wire [15:0] instruction = instruction_reg;
    
    always @(posedge clk or posedge reset) begin
        if (reset)
            instruction_reg <= 16'b0;
        else if (ir_load)
            instruction_reg <= instruction_from_mem;
    end
    
    // Instruction decode from latched instruction (16-bit format)
    wire [3:0] opcode = instruction[15:12];
    wire [1:0] rd     = instruction[11:10];
    wire [1:0] rs     = instruction[9:8];
    wire [7:0] imm    = instruction[7:0];
    
    // Immediate value extended to 16-bit
    wire [15:0] imm_extended = {8'b0, imm};
    
    // ALU result register - latches during EXECUTE
    reg [15:0] alu_result_reg;
    always @(posedge clk or posedge reset) begin
        if (reset)
            alu_result_reg <= 16'b0;
        else if (alu_latch)
            alu_result_reg <= alu_out;
    end
    
    // ALU operand B selection
    wire [15:0] alu_operand_b = reg_data2;
    
    // Write-back data selection - controlled by control unit signals
    always @(*) begin
        if (mem_to_reg)
            write_back_data = mem_read_data;
        else if (use_imm)
            write_back_data = imm_extended;
        else
            write_back_data = alu_result_reg;  // Use latched result
    end
    
    // Debug outputs
    assign alu_result = alu_out;

    // =====================================================
    // Module Instantiations
    // =====================================================
    
    // Program Counter
    program_counter pc_inst (
        .clk        (clk),
        .reset      (reset),
        .pc_enable  (pc_enable),
        .pc_load    (pc_load),
        .pc_in      (imm_extended),
        .pc_out     (pc_out)
    );
    
    // Instruction Memory (ROM)
    instruction_memory imem_inst (
        .address    (pc_out),
        .instruction(instruction_from_mem)
    );
    
    // Register File
    register_file regfile_inst (
        .clk         (clk),
        .reset       (reset),
        .write_enable(reg_write),
        .read_addr1  (rd),
        .read_addr2  (rs),
        .write_addr  (rd),
        .write_data  (write_back_data),
        .read_data1  (reg_data1),
        .read_data2  (reg_data2)
    );
    
    // ALU
    alu alu_inst (
        .operand_a  (reg_data1),
        .operand_b  (alu_operand_b),
        .alu_op     (alu_op),
        .result     (alu_out),
        .zero_flag  (zero_flag)
    );
    
    // Data Memory (RAM)
    data_memory dmem_inst (
        .clk         (clk),
        .write_enable(mem_write),
        .address     (reg_data2),
        .write_data  (reg_data1),
        .read_data   (mem_read_data)
    );
    
    // Control Unit
    control_unit ctrl_inst (
        .clk        (clk),
        .reset      (reset),
        .instruction(instruction),
        .zero_flag  (zero_flag),
        .pc_enable  (pc_enable),
        .pc_load    (pc_load),
        .reg_write  (reg_write),
        .mem_write  (mem_write),
        .mem_to_reg (mem_to_reg),
        .use_imm    (use_imm),
        .ir_load    (ir_load),
        .alu_latch  (alu_latch),
        .alu_op     (alu_op),
        .halt       (halt)
    );

endmodule

testbench/cpu_tb.v
/*
 * CPU Testbench
 * Simulates the 16-bit RISC CPU and displays execution trace
 * 
 * ADLD & CO Project - 16-bit RISC CPU
 */

`timescale 1ns/1ps

module cpu_tb;

    // Testbench signals
    reg         clk;
    reg         reset;
    wire        halt;
    wire [15:0] pc_out;
    wire [15:0] alu_result;
    
    // Instantiate CPU
    cpu_top cpu (
        .clk        (clk),
        .reset      (reset),
        .halt       (halt),
        .pc_out     (pc_out),
        .alu_result (alu_result)
    );
    
    // Clock generation (10ns period = 100MHz)
    initial begin
        clk = 0;
        forever #5 clk = ~clk;
    end
    
    // VCD dump for waveform viewing
    initial begin
        $dumpfile("cpu_waveform.vcd");
        $dumpvars(0, cpu_tb);
    end
    
    // Test sequence
    initial begin
        $display("========================================");
        $display("  16-bit RISC CPU Simulation");
        $display("  ADLD & CO Project");
        $display("========================================");
        $display("");
        
        // Apply reset
        reset = 1;
        #20;
        reset = 0;
        
        $display("Time\tPC\tInstruction\t\tR0\tR1\tR2\tR3\tALU Out\tState");
        $display("----\t--\t-----------\t\t--\t--\t--\t--\t-------\t-----");
        
        // Run simulation for enough cycles
        repeat (100) begin
            @(posedge clk);
            #1; // Small delay to let signals settle
            
            $display("%0t\t%d\t%b\t%d\t%d\t%d\t%d\t%d\t%d",
                $time,
                pc_out,
                cpu.imem_inst.memory[pc_out[7:0]],
                cpu.regfile_inst.registers[0],
                cpu.regfile_inst.registers[1],
                cpu.regfile_inst.registers[2],
                cpu.regfile_inst.registers[3],
                alu_result,
                cpu.ctrl_inst.state
            );
            
            // Stop when CPU halts
            if (halt) begin
                $display("");
                $display("========================================");
                $display("  CPU HALTED");
                $display("========================================");
                $display("");
                $display("Final Register Values:");
                $display("  R0 = %d (expected: 6)", cpu.regfile_inst.registers[0]);
                $display("  R1 = %d (expected: 3)", cpu.regfile_inst.registers[1]);
                $display("  R2 = %d (expected: 2)", cpu.regfile_inst.registers[2]);
                $display("  R3 = %d (expected: 0)", cpu.regfile_inst.registers[3]);
                $display("");
                $display("Data Memory[0] = %d (expected: 6)", cpu.dmem_inst.memory[0]);
                $display("");
                
                // Verify results
                if (cpu.regfile_inst.registers[0] == 6 &&
                    cpu.dmem_inst.memory[0] == 6) begin
                    $display("*** TEST PASSED ***");
                end else begin
                    $display("*** TEST FAILED ***");
                end
                
                $finish;
            end
        end
        
        $display("Simulation timeout - CPU did not halt");
        $finish;
    end

endmodule

cpu_waveform.vcd
$date
	Sun Jan 25 22:17:51 2026
$end
$version
	Icarus Verilog
$end
$timescale
	1ps
$end
$scope module cpu_tb $end
$var wire 16 ! pc_out [15:0] $end
$var wire 1 " halt $end
$var wire 16 # alu_result [15:0] $end
$var reg 1 $ clk $end
$var reg 1 % reset $end
$scope module cpu $end
$var wire 16 & alu_operand_b [15:0] $end
$var wire 16 ' alu_result [15:0] $end
$var wire 1 $ clk $end
$var wire 1 % reset $end
$var wire 1 ( zero_flag $end
$var wire 1 ) use_imm $end
$var wire 2 * rs [1:0] $end
$var wire 1 + reg_write $end
$var wire 16 , reg_data2 [15:0] $end
$var wire 16 - reg_data1 [15:0] $end
$var wire 2 . rd [1:0] $end
$var wire 16 / pc_out [15:0] $end
$var wire 1 0 pc_load $end
$var wire 1 1 pc_enable $end
$var wire 4 2 opcode [3:0] $end
$var wire 1 3 mem_write $end
$var wire 1 4 mem_to_reg $end
$var wire 16 5 mem_read_data [15:0] $end
$var wire 1 6 ir_load $end
$var wire 16 7 instruction_from_mem [15:0] $end
$var wire 16 8 instruction [15:0] $end
$var wire 16 9 imm_extended [15:0] $end
$var wire 8 : imm [7:0] $end
$var wire 1 " halt $end
$var wire 16 ; alu_out [15:0] $end
$var wire 4 < alu_op [3:0] $end
$var wire 1 = alu_latch $end
$var reg 16 > alu_result_reg [15:0] $end
$var reg 16 ? instruction_reg [15:0] $end
$var reg 16 @ write_back_data [15:0] $end
$scope module alu_inst $end
$var wire 16 A operand_b [15:0] $end
$var wire 1 ( zero_flag $end
$var wire 16 B operand_a [15:0] $end
$var wire 4 C alu_op [3:0] $end
$var parameter 4 D ALU_ADD $end
$var parameter 4 E ALU_AND $end
$var parameter 4 F ALU_MOV $end
$var parameter 4 G ALU_NOT $end
$var parameter 4 H ALU_OR $end
$var parameter 4 I ALU_SHL $end
$var parameter 4 J ALU_SHR $end
$var parameter 4 K ALU_SUB $end
$var parameter 4 L ALU_XOR $end
$var reg 16 M result [15:0] $end
$upscope $end
$scope module ctrl_inst $end
$var wire 1 $ clk $end
$var wire 16 N instruction [15:0] $end
$var wire 1 % reset $end
$var wire 1 ( zero_flag $end
$var wire 4 O opcode [3:0] $end
$var parameter 4 P OP_ADD $end
$var parameter 4 Q OP_AND $end
$var parameter 4 R OP_HLT $end
$var parameter 4 S OP_JMP $end
$var parameter 4 T OP_JZ $end
$var parameter 4 U OP_LD $end
$var parameter 4 V OP_LDI $end
$var parameter 4 W OP_MOV $end
$var parameter 4 X OP_NOP $end
$var parameter 4 Y OP_NOT $end
$var parameter 4 Z OP_OR $end
$var parameter 4 [ OP_SHL $end
$var parameter 4 \ OP_SHR $end
$var parameter 4 ] OP_ST $end
$var parameter 4 ^ OP_SUB $end
$var parameter 4 _ OP_XOR $end
$var parameter 3 ` STATE_DECODE $end
$var parameter 3 a STATE_EXECUTE $end
$var parameter 3 b STATE_FETCH $end
$var parameter 3 c STATE_HALT $end
$var parameter 3 d STATE_MEMORY $end
$var parameter 3 e STATE_WRITEBACK $end
$var reg 1 = alu_latch $end
$var reg 4 f alu_op [3:0] $end
$var reg 1 " halt $end
$var reg 1 6 ir_load $end
$var reg 1 4 mem_to_reg $end
$var reg 1 3 mem_write $end
$var reg 3 g next_state [2:0] $end
$var reg 4 h opcode_reg [3:0] $end
$var reg 1 1 pc_enable $end
$var reg 1 0 pc_load $end
$var reg 1 + reg_write $end
$var reg 3 i state [2:0] $end
$var reg 1 ) use_imm $end
$upscope $end
$scope module dmem_inst $end
$var wire 1 $ clk $end
$var wire 16 j read_data [15:0] $end
$var wire 1 3 write_enable $end
$var wire 16 k write_data [15:0] $end
$var wire 16 l address [15:0] $end
$var integer 32 m i [31:0] $end
$upscope $end
$scope module imem_inst $end
$var wire 16 n instruction [15:0] $end
$var wire 16 o address [15:0] $end
$upscope $end
$scope module pc_inst $end
$var wire 1 $ clk $end
$var wire 1 1 pc_enable $end
$var wire 16 p pc_in [15:0] $end
$var wire 1 0 pc_load $end
$var wire 1 % reset $end
$var reg 16 q pc_out [15:0] $end
$upscope $end
$scope module regfile_inst $end
$var wire 1 $ clk $end
$var wire 2 r read_addr1 [1:0] $end
$var wire 2 s read_addr2 [1:0] $end
$var wire 16 t read_data1 [15:0] $end
$var wire 16 u read_data2 [15:0] $end
$var wire 1 % reset $end
$var wire 2 v write_addr [1:0] $end
$var wire 16 w write_data [15:0] $end
$var wire 1 + write_enable $end
$var integer 32 x i [31:0] $end
$upscope $end
$upscope $end
$upscope $end
$enddefinitions $end
$comment Show the parameter values. $end
$dumpall
b100 e
b11 d
b101 c
b0 b
b10 a
b1 `
b101 _
b10 ^
b1011 ]
b1000 \
b111 [
b100 Z
b110 Y
b0 X
b1111 W
b1001 V
b1010 U
b1101 T
b1100 S
b1110 R
b11 Q
b1 P
b101 L
b10 K
b1000 J
b111 I
b100 H
b110 G
b1111 F
b11 E
b1 D
$end
#0
$dumpvars
b100 x
b0 w
b0 v
b0 u
b0 t
b0 s
b0 r
b0 q
b0 p
b0 o
b1001000000000101 n
b100000000 m
b0 l
b0 k
b0 j
b0 i
b0 h
b1 g
b0 f
b0 O
b0 N
b0 M
b0 C
b0 B
b0 A
b0 @
b0 ?
b0 >
0=
b0 <
b0 ;
b0 :
b0 9
b0 8
b1001000000000101 7
16
b0 5
04
03
b0 2
11
00
b0 /
b0 .
b0 -
b0 ,
0+
b0 *
0)
1(
b0 '
b0 &
1%
0$
b0 #
0"
b0 !
$end
#5000
b100 x
1$
#10000
0$
#15000
b100 x
1$
#20000
0$
0%
#25000
b1001 <
b1001 C
b1001 f
b1001 2
b101 9
b101 p
b101 :
b1001 O
06
01
b10 g
b1001010000000011 7
b1001010000000011 n
b1001000000000101 8
b1001000000000101 ?
b1001000000000101 N
b1 i
b1 !
b1 /
b1 o
b1 q
1$
#30000
0$
#35000
1=
b1001 <
b1001 C
b1001 f
b100 g
b1001 h
b10 i
1$
#40000
0$
#45000
b101 @
b101 w
1)
1+
b0 <
b0 C
b0 f
0=
b0 g
b100 i
1$
#50000
0$
#55000
b0 @
b0 w
11
16
0)
0+
b1 g
b101 -
b101 B
b101 k
b101 t
b101 &
b101 A
b101 ,
b101 l
b101 u
b0 i
1$
#60000
0$
#65000
b0 -
b0 B
b0 k
b0 t
b1 .
b1 r
b1 v
b11 9
b11 p
b11 :
b1001 <
b1001 C
b1001 f
06
01
b10 g
b1000100000000 7
b1000100000000 n
b1001010000000011 8
b1001010000000011 ?
b1001010000000011 N
b1 i
b10 !
b10 /
b10 o
b10 q
1$
#70000
0$
#75000
1=
b1001 <
b1001 C
b1001 f
b100 g
b10 i
1$
#80000
0$
#85000
b11 @
b11 w
1)
1+
b0 <
b0 C
b0 f
0=
b0 g
b100 i
1$
#90000
0$
#95000
b0 @
b0 w
11
16
0)
0+
b1 g
b11 -
b11 B
b11 k
b11 t
b0 i
1$
#100000
0$
#105000
0(
b1000 #
b1000 '
b1000 ;
b1000 M
b1 2
b101 -
b101 B
b101 k
b101 t
b0 .
b0 r
b0 v
b11 &
b11 A
b11 ,
b11 l
b11 u
b1 *
b1 s
b0 9
b0 p
b0 :
b1 O
b1 <
b1 C
b1 f
06
01
b10 g
b1001100000000010 7
b1001100000000010 n
b1000100000000 8
b1000100000000 ?
b1000100000000 N
b1 i
b11 !
b11 /
b11 o
b11 q
1$
#110000
0$
#115000
1=
b1 <
b1 C
b1 f
b100 g
b1 h
b10 i
1$
#120000
0$
#125000
1(
b0 #
b0 '
b0 ;
b0 M
b1000 @
b1000 w
1+
b0 <
b0 C
b0 f
0=
b0 g
b1000 >
b100 i
1$
#130000
0$
#135000
11
16
0+
b1 g
b1000 -
b1000 B
b1000 k
b1000 t
b0 i
1$
#140000
0$
#145000
1(
b0 #
b0 '
b0 ;
b0 M
b1001 2
b0 -
b0 B
b0 k
b0 t
b10 .
b10 r
b10 v
b1000 &
b1000 A
b1000 ,
b1000 l
b1000 u
b0 *
b0 s
b10 9
b10 p
b10 :
b1001 O
b1001 <
b1001 C
b1001 f
06
01
b10 g
b10001000000000 7
b10001000000000 n
b1001100000000010 8
b1001100000000010 ?
b1001100000000010 N
b1 i
b100 !
b100 /
b100 o
b100 q
1$
#150000
0$
#155000
1=
b1001 <
b1001 C
b1001 f
b100 g
b1001 h
b10 i
1$
#160000
0$
#165000
b10 @
b10 w
1)
1+
b0 <
b0 C
b0 f
0=
b0 g
b0 >
b100 i
1$
#170000
0$
#175000
b0 @
b0 w
11
16
0)
0+
b1 g
b10 -
b10 B
b10 k
b10 t
b0 i
1$
#180000
0$
#185000
0(
b110 #
b110 '
b110 ;
b110 M
b10 2
b1000 -
b1000 B
b1000 k
b1000 t
b0 .
b0 r
b0 v
b10 &
b10 A
b10 ,
b10 l
b10 u
b10 *
b10 s
b0 9
b0 p
b0 :
b10 O
b10 <
b10 C
b10 f
06
01
b10 g
b1001110000000000 7
b1001110000000000 n
b10001000000000 8
b10001000000000 ?
b10001000000000 N
b1 i
b101 !
b101 /
b101 o
b101 q
1$
#190000
0$
#195000
1=
b10 <
b10 C
b10 f
b100 g
b10 h
b10 i
1$
#200000
0$
#205000
1(
b0 #
b0 '
b0 ;
b0 M
b110 @
b110 w
1+
b0 <
b0 C
b0 f
0=
b0 g
b110 >
b100 i
1$
#210000
0$
#215000
11
16
0+
b1 g
b110 -
b110 B
b110 k
b110 t
b0 i
1$
#220000
0$
#225000
1(
b0 #
b0 '
b0 ;
b0 M
b1001 2
b0 -
b0 B
b0 k
b0 t
b11 .
b11 r
b11 v
b110 &
b110 A
b110 ,
b110 l
b110 u
b0 *
b0 s
b1001 O
b1001 <
b1001 C
b1001 f
06
01
b10 g
b1011001100000000 7
b1011001100000000 n
b1001110000000000 8
b1001110000000000 ?
b1001110000000000 N
b1 i
b110 !
b110 /
b110 o
b110 q
1$
#230000
0$
#235000
1=
b1001 <
b1001 C
b1001 f
b100 g
b1001 h
b10 i
1$
#240000
0$
#245000
b0 @
b0 w
1)
1+
b0 <
b0 C
b0 f
0=
b0 g
b0 >
b100 i
1$
#250000
0$
#255000
11
16
0)
0+
b1 g
b0 i
1$
#260000
0$
#265000
b1011 2
b110 -
b110 B
b110 k
b110 t
b0 .
b0 r
b0 v
b0 &
b0 A
b0 ,
b0 l
b0 u
b11 *
b11 s
b1011 O
b1011 <
b1011 C
b1011 f
06
01
b10 g
b1110000000000000 7
b1110000000000000 n
b1011001100000000 8
b1011001100000000 ?
b1011001100000000 N
b1 i
b111 !
b111 /
b111 o
b111 q
1$
#270000
0$
#275000
1=
b1011 <
b1011 C
b1011 f
b11 g
b1011 h
b10 i
1$
#280000
0$
#285000
13
b0 <
b0 C
b0 f
0=
b100 g
b11 i
1$
#290000
0$
#295000
03
b0 g
b100 i
b110 5
b110 j
1$
#300000
0$
#305000
11
16
b1 g
b0 i
1$
#310000
0$
#315000
b0 5
b0 j
bx 7
bx n
b1110 <
b1110 C
b1110 f
06
01
b101 g
b1110 2
b110 &
b110 A
b110 ,
b110 l
b110 u
b0 *
b0 s
b1110 O
b1000 !
b1000 /
b1000 o
b1000 q
b1 i
b1110000000000000 8
b1110000000000000 ?
b1110000000000000 N
1$
#320000
0$
#325000
1"
b0 <
b0 C
b0 f
b1110 h
b101 i
1$
